FortniteAPIAsync/__init__.py
FortniteAPIAsync/api.py
FortniteAPIAsync/cosmetics.py
FortniteAPIAsync/enums.py
FortniteAPIAsync/exceptions.py
FortniteAPIAsync/http.py
FortniteAPIAsync/stats.py
FortniteAPIAsync-0.1.7.dist-info/METADATA
FortniteAPIAsync-0.1.7.dist-info/WHEEL
FortniteAPIAsync-0.1.7.dist-info/top_level.txt
FortniteAPIAsync-0.1.7.dist-info/RECORD
