Metadata-Version: 2.1
Name: FortniteAPIAsync
Version: 0.1.7
Summary: Asynchronous Python wrapper for Fortnite-API.com.
Home-page: https://github.com/xMistt/FortniteAPIAsync
Author: xMistt
Project-URL: Documentation, https://github.com/xMistt/FortniteAPIAsync/wiki
Project-URL: Issues, https://github.com/xMistt/FortniteAPIAsync/issues
Classifier: Programming Language :: Python :: 3
Classifier: License :: OSI Approved :: MIT License
Classifier: Operating System :: OS Independent
